{
  "name": {
    "en": "Multiple buyers"
  },
  "description": {
    "en": "In some cases, a single contracting process involves multiple buyers (for example, a framework that different organizations can buy from). In these cases, the multiple buyers extension can be used to specify a distinct buyer for each award or contract. "
  },
  "documentationUrl": {
    "en": "https://extensions.open-contracting.org/en/extensions/contract_buyer/"
  },
  "compatibility": [
    "1.1"
  ],
  "schemas": [
    "release-schema.json"
  ],
  "contactPoint": {
    "name": "Open Contracting Partnership",
    "email": "data@open-contracting.org"
  }
}
